bashlyk/__init__.py
tests/__init__.py
tests/test_run.py
bashlyk-0.0.0.dist-info/LICENSE
bashlyk-0.0.0.dist-info/METADATA
bashlyk-0.0.0.dist-info/WHEEL
bashlyk-0.0.0.dist-info/top_level.txt
bashlyk-0.0.0.dist-info/RECORD
